cellxgene_census/__init__.py
cellxgene_census/_experiment.py
cellxgene_census/_get_anndata.py
cellxgene_census/_open.py
cellxgene_census/_presence_matrix.py
cellxgene_census/_release_directory.py
cellxgene_census/_util.py
cellxgene_census/py.typed
cellxgene_census/_testing/__init__.py
cellxgene_census/_testing/logger_proxy.py
cellxgene_census/experimental/__init__.py
cellxgene_census/experimental/_embedding.py
cellxgene_census/experimental/_embedding_search.py
cellxgene_census/experimental/ml/__init__.py
cellxgene_census/experimental/ml/encoders.py
cellxgene_census/experimental/ml/pytorch.py
cellxgene_census/experimental/ml/huggingface/__init__.py
cellxgene_census/experimental/ml/huggingface/cell_dataset_builder.py
cellxgene_census/experimental/ml/huggingface/geneformer_tokenizer.py
cellxgene_census/experimental/pp/__init__.py
cellxgene_census/experimental/pp/_highly_variable_genes.py
cellxgene_census/experimental/pp/_online.py
cellxgene_census/experimental/pp/_stats.py
cellxgene_census/experimental/util/__init__.py
cellxgene_census/experimental/util/_eager_iter.py
cellxgene_census-1.16.2.dist-info/LICENSE
cellxgene_census-1.16.2.dist-info/METADATA
cellxgene_census-1.16.2.dist-info/WHEEL
cellxgene_census-1.16.2.dist-info/top_level.txt
cellxgene_census-1.16.2.dist-info/RECORD
