Metadata-Version: 2.1
Name: cellxgene-census
Version: 1.16.2
Summary: API to facilitate the use of the CZ CELLxGENE Discover Census. For more information about the API and the project visit https://github.com/chanzuckerberg/cellxgene-census/
Author-email: Chan Zuckerberg Initiative Foundation <soma@chanzuckerberg.com>
License: MIT
Project-URL: homepage, https://github.com/chanzuckerberg/cellxgene-census
Project-URL: repository, https://github.com/chanzuckerberg/cellxgene-census
Classifier: Development Status :: 4 - Beta
Classifier: Intended Audience :: Developers
Classifier: Intended Audience :: Information Technology
Classifier: Intended Audience :: Science/Research
Classifier: License :: OSI Approved :: MIT License
Classifier: Programming Language :: Python
Classifier: Topic :: Scientific/Engineering :: Bio-Informatics
Classifier: Operating System :: POSIX :: Linux
Classifier: Operating System :: MacOS :: MacOS X
Classifier: Programming Language :: Python :: 3.10
Classifier: Programming Language :: Python :: 3.11
Classifier: Programming Language :: Python :: 3.12
Requires-Python: <3.13,>=3.10
License-File: LICENSE
Requires-Dist: tiledbsoma !=1.14.1,>=1.12.3
Requires-Dist: anndata
Requires-Dist: numpy <2.0,>=1.23
Requires-Dist: requests
Requires-Dist: typing-extensions
Requires-Dist: s3fs >=2021.06.1
Provides-Extra: doc
Requires-Dist: nbsphinx ; extra == 'doc'
Requires-Dist: myst-parser ; extra == 'doc'
Requires-Dist: sphinx-rtd-theme ; extra == 'doc'
Requires-Dist: gitpython ; extra == 'doc'
Requires-Dist: sphinx <7.0.0 ; extra == 'doc'
Provides-Extra: experimental
Requires-Dist: torch ; extra == 'experimental'
Requires-Dist: torchdata ~=0.7 ; extra == 'experimental'
Requires-Dist: scikit-learn >=1.2 ; extra == 'experimental'
Requires-Dist: scikit-misc <0.4,>=0.2 ; extra == 'experimental'
Requires-Dist: datasets ~=2.0 ; extra == 'experimental'
Requires-Dist: tdigest ~=0.5 ; extra == 'experimental'
Requires-Dist: tiledb-vector-search ~=0.2 ; extra == 'experimental'
